oetcloudmodule/__init__.py
oetcloudmodule/add.py
oetcloudmodule/hello.py
oetcloudmodule/kubeexe copy.py
oetcloudmodule/kubeexe.py
oetcloudmodule/subtract.py
oetcloudmodule/extras/__init__.py
oetcloudmodule/extras/multiply.py
oetcloudmodule/templates/k8-jinja.yaml
oetcloudmodule/templates/k8-job.yaml
oetcloudmodule-0.1.1.dist-info/METADATA
oetcloudmodule-0.1.1.dist-info/WHEEL
oetcloudmodule-0.1.1.dist-info/entry_points.txt
oetcloudmodule-0.1.1.dist-info/top_level.txt
oetcloudmodule-0.1.1.dist-info/RECORD
